[
  {
    "hex_start": "54 45 58 54 10 00 00 00 70 1C 00 00 00 00 00 00 00 00",
    "strings": [
      {
        "jp_string": "<pc>のさおが　冷気を放った！",
        "en_string": "<pc>'s rod released a blast of cold air!"
      },
      {
        "jp_string": "<pc>のさおが　燃え上がった！",
        "en_string": "<pc>'s rod burned up!"
      },
      {
        "jp_string": "<pc>のさおが　輝きだした！",
        "en_string": "<pc>'s rod started shining!"
      },
      {
        "jp_string": "<pc>は　さおをゆるめた！",
        "en_string": "<pc> loosened the rod!"
      },
      {
        "jp_string": "<pc>は　さおを引いた！",
        "en_string": "<pc> reeled in the rod!"
      },
      {
        "jp_string": "<pc>は　全力で引いた！",
        "en_string": "<pc> reeled with full power!"
      },
      {
        "jp_string": "<pc>は　釣り上げるのを　あきらめた。",
        "en_string": "<pc> gave up on fishing."
      },
      {
        "jp_string": "<pc>は　闇の力で引いた！",
        "en_string": "<pc> reeled with dark power!"
      },
      {
        "jp_string": "あきらめる",
        "en_string": "Give Up"
      },
      {
        "line_break": true,
        "jp_string": "あんこくの力で さかなに行動を させづらくする",
        "en_string": "Fish have|trouble acting in|darkness power."
      },
      {
        "line_break": true,
        "jp_string": "きせきの力で 釣りざおを引く 食いつき度が回復",
        "en_string": "Reel the rod|with the power|of a miracle."
      },
      {
        "jp_string": "きせきの力で引く",
        "en_string": "Miracle Reel"
      },
      {
        "jp_string": "くいつき度アップ",
        "en_string": "Biting Rate Up"
      },
      {
        "jp_string": "くいつき度アップは 覚えているだけで　常にくいつき度が 少し　上がるようになります。",
        "en_string": "Biting Rate Up increases the chance that harder fish will bite."
      },
      {
        "jp_string": "さおゆるめ回復量アップ",
        "en_string": "Loosening Recovery Up"
      },
      {
        "jp_string": "さおゆるめ回復量アップは 覚えているだけで　さおをゆるめた時の 回復量が　少し　上がるようになります。",
        "en_string": "Loosening Recovery Up will increase the amount recovered when you loose your line."
      },
      {
        "jp_string": "さおをゆるめて くいつき度を 回復させる",
        "en_string": "Loose your line|and restore|biting frequency."
      },
      {
        "jp_string": "さおをゆるめる",
        "en_string": "Loosen Rod"
      },
      {
        "jp_string": "さおをゆるめる回数が　<%dL_KISEKI>回増えた！",
        "en_string": "Number of times to loosen rod increased by <%dL_KISEKI>!"
      },
      {
        "line_break": true,
        "jp_string": "さおを引いて さかなを近くに 引き寄せる",
        "en_string": "Reel your line|and pull the|fish closer."
      },
      {
        "jp_string": "さおを引く",
        "en_string": "Reel Rod"
      },
      {
        "jp_string": "さかなが　トゲを出した！",
        "en_string": "The fish's spikes came out!"
      },
      {
        "jp_string": "さかなが　地面にもぐった！",
        "en_string": "The fish dove to the ground!"
      },
      {
        "jp_string": "さかなが　水流に乗って　遠ざかっていく！",
        "en_string": "The fish rides on a current and swims away!"
      },
      {
        "jp_string": "さかなが　水流を巻き起こした！",
        "en_string": "The fish caused a water current!"
      },
      {
        "jp_string": "さかなが　水面に飛び上がった！",
        "en_string": "The fish jumped to the surface!"
      },
      {
        "jp_string": "さかなが　目を覚ました！",
        "en_string": "The fish woke up!"
      },
      {
        "jp_string": "さかなの　つうこんのかみつき！",
        "en_string": "The fish bit with grief!"
      },
      {
        "jp_string": "さかなの　超ちからため！",
        "en_string": "The fish used super strength!"
      },
      {
        "jp_string": "さかなのスミが　晴れた！",
        "en_string": "The fish swelled with ink!"
      },
      {
        "jp_string": "さかなのテンションが　戻った。",
        "en_string": "The fish's tension is gone."
      },
      {
        "jp_string": "さかなのトゲが　ひっこんだ。",
        "en_string": "The fish retracted its spikes."
      },
      {
        "jp_string": "さかなの凍結状態が　なおった。",
        "en_string": "The fish is no longer frozen."
      },
      {
        "jp_string": "さかなの力が抜けていて　多めに引き寄せられた！",
        "en_string": "The fish is weak and was reeled in far!"
      },
      {
        "jp_string": "さかなの行動に反応して　ルアーが輝きだした！ やいばのルアーのチカラで　さかなを引き寄せた！",
        "en_string": "The lure begins to shine! The Blade Lure's power attracted fish!"
      },
      {
        "jp_string": "さかなの闇が　晴れた。",
        "en_string": "The dark fish cleared up."
      },
      {
        "jp_string": "さかなは　あごをゆらしている。",
        "en_string": "The fish is shaking its chin."
      },
      {
        "jp_string": "さかなは　くるくると　回転した。",
        "en_string": "The fish turned around."
      },
      {
        "jp_string": "さかなは　こちらを威嚇している！",
        "en_string": "The fish is being intimidating!"
      },
      {
        "jp_string": "さかなは　じたばた暴れている！",
        "en_string": "The fish is on a rampage!"
      },
      {
        "jp_string": "さかなは　じっとしている。",
        "en_string": "The fish is being still."
      },
      {
        "jp_string": "さかなは　すばやく泳ぎ去った！",
        "en_string": "The fish quickly swam away!"
      },
      {
        "jp_string": "さかなは　ちからをためた！",
        "en_string": "The fish psyched up!"
      },
      {
        "jp_string": "さかなは　はげしく　かみついた！",
        "en_string": "The fish bit hard!"
      },
      {
        "jp_string": "さかなは　ぼーっとしている。",
        "en_string": "The fish is scared."
      },
      {
        "jp_string": "さかなは　ゆっくり泳いでいる。",
        "en_string": "The fish is swimming slowly."
      },
      {
        "jp_string": "さかなは　ゆらゆらしている。",
        "en_string": "The fish is swaying."
      },
      {
        "jp_string": "さかなは　ゆらゆらと　ただよっている。",
        "en_string": "The fish is floating around."
      },
      {
        "jp_string": "さかなは　ようすをうかがっている。",
        "en_string": "The fish is waiting."
      },
      {
        "jp_string": "さかなは　コロコロしている。",
        "en_string": "The fish is rolling around."
      },
      {
        "jp_string": "さかなは　スミを出した！",
        "en_string": "The fish let out ink!"
      },
      {
        "jp_string": "さかなは　トゲを動かした！",
        "en_string": "The fish moved its spine!"
      },
      {
        "jp_string": "さかなは　ヒゲを　ふるわせている。",
        "en_string": "The fish is shaking its whiskers."
      },
      {
        "jp_string": "さかなは　凍り付いていて　動けない！",
        "en_string": "The fish is frozen and can't move!"
      },
      {
        "jp_string": "さかなは　吻を大きく　振り回した！",
        "en_string": "The fish swung its big snout!"
      },
      {
        "jp_string": "さかなは　地面にもぐっている。",
        "en_string": "The fish is submerged in the ground."
      },
      {
        "jp_string": "さかなは　大きく　体を動かした。",
        "en_string": "The fish moved a lot."
      },
      {
        "jp_string": "さかなは　大きくクチを　開けた！ 次の行動は　やばそうだ！",
        "en_string": "The fish opened its mouth wide! Its next action seems dangerous!"
      },
      {
        "jp_string": "さかなは　大きく動き　波を起こした！",
        "en_string": "The fish moved and made big waves!"
      },
      {
        "jp_string": "さかなは　大きな身体を　勢いよく動かした！",
        "en_string": "The fish moved its body vigorously!"
      },
      {
        "jp_string": "さかなは　大暴れをした！",
        "en_string": "The fish went on a rampage!"
      },
      {
        "jp_string": "さかなは　尾ひれを　ゆらめかせている。",
        "en_string": "The fish is shaking its tail fin."
      },
      {
        "jp_string": "さかなは　必死に泳いでいる！",
        "en_string": "The fish is swimming desperately!"
      },
      {
        "jp_string": "さかなは　必死に海底をはった！",
        "en_string": "The fish desperately hit the sea floor!"
      },
      {
        "jp_string": "さかなは　水の中を　旋回している。",
        "en_string": "The fish is turning in the water."
      },
      {
        "jp_string": "さかなは　水底に　尾ひれを打ちつけた！",
        "en_string": "The fish hit its tail fin on the sea floor!"
      },
      {
        "jp_string": "さかなは　海底で飛び跳ねた！",
        "en_string": "The fish jumped out of the seabed!"
      },
      {
        "jp_string": "さかなは　疲れて　ぐったりしている。",
        "en_string": "The fish is tired."
      },
      {
        "jp_string": "さかなは　疲れているようだ。",
        "en_string": "The fish seems tired."
      },
      {
        "jp_string": "さかなは　眠っている。",
        "en_string": "The fish is sleeping."
      },
      {
        "jp_string": "さかなは　闇に包まれ　おびえている！",
        "en_string": "The fish is wrapped in darkness and scared!"
      },
      {
        "jp_string": "さかなは　電気を放電した！",
        "en_string": "The fish discharged electricity!"
      },
      {
        "jp_string": "さかなは　電気を溜めている！",
        "en_string": "The fish is storing electricity!"
      },
      {
        "jp_string": "さかなは　首をはげしく振った！",
        "en_string": "The fish violently shook its head!"
      },
      {
        "jp_string": "さかなを　凍らせた！",
        "en_string": "The fish froze!"
      },
      {
        "jp_string": "さかなを　地面から　引きずり出した！",
        "en_string": "Dragged the fish from off the ground!"
      },
      {
        "jp_string": "さかなを　闇で包み込んだ！",
        "en_string": "Wrapped the fish in darkness!"
      },
      {
        "line_break": true,
        "jp_string": "さかなを倍の力で 引き寄せるが くいつき度が半減",
        "en_string": "Attracts stronger|fish, but bite|rate is halved."
      },
      {
        "jp_string": "さらに引き寄せる力アップ",
        "en_string": "Attraction Power Up"
      },
      {
        "jp_string": "さらに引き寄せる力アップは 覚えているだけで　常に　引き寄せる力が より　上がるようになります。",
        "en_string": "Attraction Power Up will increase the rate that fish will be attracted."
      },
      {
        "jp_string": "しかし　うまく発動しなかった！",
        "en_string": "But...it didn't work!"
      },
      {
        "jp_string": "しかし　なにもおこらなかった。",
        "en_string": "But...nothing happened."
      },
      {
        "jp_string": "そよ風の浜",
        "en_string": "Breezy Beach"
      },
      {
        "jp_string": "なかまのさかなが　集まって　暴れた！",
        "en_string": "The fellow fish gathered and rampaged!"
      },
      {
        "jp_string": "なんと　さかなの状態異常が　解けてしまった！",
        "en_string": "Suddenly, the fish's abnormal status has been solved!"
      },
      {
        "jp_string": "みかがみの泉",
        "en_string": "Mirror Fountain"
      },
      {
        "jp_string": "オアシス",
        "en_string": "Oasis"
      },
      {
        "jp_string": "キングサイズ確率アップ",
        "en_string": "King Size Chance Up"
      },
      {
        "jp_string": "キングサイズ確率アップは 覚えているだけで　キングサイズの魚が かかりやすく　なります。",
        "en_string": "King Size Chance Up makes it easier to catch king sized fish."
      },
      {
        "jp_string": "クデゥスの泉",
        "en_string": "Kudus Fountain"
      },
      {
        "jp_string": "コバルト池",
        "en_string": "Cobalt Pond"
      },
      {
        "jp_string": "スイカは　はげしい水の流れにさらわれた！",
        "en_string": "The watermelon was taken by the strong current!"
      },
      {
        "jp_string": "スイカは　プカプカと　ただよっている。",
        "en_string": "The watermelon is floating."
      },
      {
        "jp_string": "スイカは　水の流れにさらわれた！",
        "en_string": "The watermelon was taken by the current!"
      },
      {
        "jp_string": "スライムの池",
        "en_string": "Slime Pond"
      },
      {
        "jp_string": "ソーダの泉",
        "en_string": "Soda Fountain"
      },
      {
        "jp_string": "トゲで　ルアーが削られる！",
        "en_string": "The lure is scraped with thorns!"
      },
      {
        "jp_string": "トゲトゲルアーのチカラで くいつき度が　減らなかった！",
        "en_string": "The splinter lure's power did not reduce the biting chance!"
      },
      {
        "line_break": true,
        "jp_string": "ナツリ特製の旬の 秘められた力で 釣りさおを引く",
        "en_string": "A rod made by|Natsuri with a|hidden power."
      },
      {
        "jp_string": "ハニーレイク",
        "en_string": "Honey Lake"
      },
      {
        "jp_string": "ビッグサイズ確率アップ",
        "en_string": "Big Size Chance Up"
      },
      {
        "jp_string": "ビッグサイズ確率アップは 覚えているだけで　ビッグサイズの魚が かかりやすく　なります。",
        "en_string": "Big Size Chance Up makes it easier to catch big sized fish."
      },
      {
        "jp_string": "ヘドロの沼地",
        "en_string": "Muddy Swamp"
      },
      {
        "jp_string": "ミス",
        "en_string": "Miss"
      },
      {
        "jp_string": "ミレナ海岸",
        "en_string": "Milena Coast"
      },
      {
        "jp_string": "ルアーが　波にさらわれる！",
        "en_string": "The waves took your lure!"
      },
      {
        "jp_string": "上流",
        "en_string": "Upstr."
      },
      {
        "jp_string": "下流",
        "en_string": "Dwnst."
      },
      {
        "jp_string": "井戸水",
        "en_string": "Wellwater"
      },
      {
        "jp_string": "何も起こらない",
        "en_string": "Nothing happens"
      },
      {
        "jp_string": "全力で引く",
        "en_string": "Full Power Reel"
      },
      {
        "jp_string": "内海",
        "en_string": "Cove"
      },
      {
        "jp_string": "南の海",
        "en_string": "S. Sea"
      },
      {
        "jp_string": "噴水",
        "en_string": "Fntn."
      },
      {
        "jp_string": "回復の泉",
        "en_string": "Heal Fntn."
      },
      {
        "jp_string": "地下水",
        "en_string": "Landwater"
      },
      {
        "jp_string": "地底湖",
        "en_string": "Und. Lake"
      },
      {
        "jp_string": "地流池",
        "en_string": "Land Pond"
      },
      {
        "jp_string": "堀",
        "en_string": "Mo."
      },
      {
        "jp_string": "大浴場",
        "en_string": "Big Bath"
      },
      {
        "jp_string": "天使のルアーのチカラで　くいつき度が増えた！",
        "en_string": "The angel lure's power has increased biting chance!"
      },
      {
        "jp_string": "天流池",
        "en_string": "Angelpond"
      },
      {
        "jp_string": "女王の池",
        "en_string": "Queen's Pond"
      },
      {
        "jp_string": "宝箱は　はげしい水の流れにさらわれた！",
        "en_string": "The chest was taken by a strong current!"
      },
      {
        "jp_string": "宝箱は　ゆらゆらと　ただよっている。",
        "en_string": "The chest is floating."
      },
      {
        "jp_string": "宝箱は　水の流れにさらわれた！",
        "en_string": "The chest was taken by a current!"
      },
      {
        "jp_string": "宣誓の滝",
        "en_string": "Oath Waterf."
      },
      {
        "jp_string": "川",
        "en_string": "Rv."
      },
      {
        "jp_string": "川の水",
        "en_string": "Rv. Water"
      },
      {
        "jp_string": "川上流",
        "en_string": "Upstream"
      },
      {
        "jp_string": "川下流",
        "en_string": "Downstrm."
      },
      {
        "jp_string": "巡礼の泉",
        "en_string": "Pilgrim Ftn."
      },
      {
        "jp_string": "幻影の川",
        "en_string": "Phantom Rv."
      },
      {
        "jp_string": "旬のスイカは　はげしい水の流れにさらわれた！",
        "en_string": "The watermelon was taken by a strong current!"
      },
      {
        "jp_string": "旬のスイカは　プカプカと　ただよっている。",
        "en_string": "The watermelon is floating."
      },
      {
        "jp_string": "旬のスイカは　水の流れにさらわれた！",
        "en_string": "The watermelon was taken by a current!"
      },
      {
        "jp_string": "旬の力で引く",
        "en_string": "Season Power Reel"
      },
      {
        "jp_string": "時雨の泉",
        "en_string": "Drizzle Spg."
      },
      {
        "jp_string": "東の川",
        "en_string": "E. River"
      },
      {
        "jp_string": "東の浜",
        "en_string": "E. Beach"
      },
      {
        "jp_string": "東の海",
        "en_string": "E. Sea"
      },
      {
        "jp_string": "毒の海",
        "en_string": "Psn. Sea"
      },
      {
        "jp_string": "毒沼",
        "en_string": "Swamp"
      },
      {
        "jp_string": "水たまり",
        "en_string": "Puddle"
      },
      {
        "jp_string": "水堀",
        "en_string": "Moat"
      },
      {
        "jp_string": "水場",
        "en_string": "Field"
      },
      {
        "jp_string": "水没地帯",
        "en_string": "Submerged A."
      },
      {
        "jp_string": "水流が　収まった。",
        "en_string": "The water flow stopped."
      },
      {
        "jp_string": "水路",
        "en_string": "Wtrwy."
      },
      {
        "jp_string": "氷の力で引く",
        "en_string": "Ice Power Reel"
      },
      {
        "jp_string": "氷の重さで　引き寄せにくい！",
        "en_string": "The ice's weight makes attraction hard!"
      },
      {
        "jp_string": "池",
        "en_string": "Pd."
      },
      {
        "jp_string": "泉",
        "en_string": "Ft."
      },
      {
        "jp_string": "波が　おさまった。",
        "en_string": "The waves stopped."
      },
      {
        "jp_string": "海",
        "en_string": "Sea"
      },
      {
        "jp_string": "海水",
        "en_string": "Seawr."
      },
      {
        "jp_string": "清澄の冷泉",
        "en_string": "Clear Cold Ftn."
      },
      {
        "jp_string": "温泉",
        "en_string": "Spa"
      },
      {
        "jp_string": "湖",
        "en_string": "Lk."
      },
      {
        "jp_string": "湿原",
        "en_string": "Bog"
      },
      {
        "jp_string": "湿地帯",
        "en_string": "Wetlands"
      },
      {
        "jp_string": "滝",
        "en_string": "Wf."
      },
      {
        "jp_string": "滝壺",
        "en_string": "Wf. B."
      },
      {
        "jp_string": "潮だまり",
        "en_string": "Tide Pool"
      },
      {
        "jp_string": "炎の力で引く",
        "en_string": "Fire Power Reel"
      },
      {
        "line_break": true,
        "jp_string": "炎の力を込めて 釣りざおを引く 威力にムラがある",
        "en_string": "The reeling power|of flames is|uneven."
      },
      {
        "jp_string": "西の川",
        "en_string": "W. River"
      },
      {
        "jp_string": "西の浜",
        "en_string": "W. Beach"
      },
      {
        "jp_string": "貯水槽道しるべの川",
        "en_string": "Reservoir Signpost River"
      },
      {
        "jp_string": "釣りざおの冷気で さかなを凍らせる",
        "en_string": "Freeze fish with the rod's cold air."
      },
      {
        "jp_string": "釣りとくぎ「きせきの力で引く」が使える",
        "en_string": "You can use the fishing skill 'Miracle Reel'."
      },
      {
        "jp_string": "釣りとくぎ「全力で引く」が使える",
        "en_string": "You can use the fishing skill 'Full Power Reel'."
      },
      {
        "jp_string": "釣りとくぎ「旬の力で引く」が使える",
        "en_string": "You can use the fishing skill 'Season Power Reel'."
      },
      {
        "jp_string": "釣りとくぎ「氷の力で引く」が使える",
        "en_string": "You can use the fishing skill 'Ice Power Reel'."
      },
      {
        "jp_string": "釣りとくぎ「炎の力で引く」が使える",
        "en_string": "You can use the fishing skill 'Fire Power Reel'."
      },
      {
        "jp_string": "釣りとくぎ「闇の力で引く」が使える",
        "en_string": "You can use the fishing skill 'Dark Power Reel'."
      },
      {
        "jp_string": "釣りをあきらめて さかなを逃がす",
        "en_string": "Give up fishing and let it go"
      },
      {
        "jp_string": "釣り会心率0.5％アップ",
        "en_string": "Fishing Critical Rate 0.5% Up"
      },
      {
        "jp_string": "釣り会心率0.5％アップは 覚えているだけで　常に釣り会心率が 0.5％分　上がるようになります。",
        "en_string": "Fishing Critical Rate 0.5% Up makes it easier to get a critical reel."
      },
      {
        "jp_string": "闇の力で引く",
        "en_string": "Dark Power Reel"
      },
      {
        "jp_string": "？？？",
        "en_string": "???"
      },
      {
        "jp_string": "？？？は　はげしい水の流れにさらわれた！",
        "en_string": "??? was taken by a strong current!"
      },
      {
        "jp_string": "？？？は　ゆらゆらと　ただよっている。",
        "en_string": "??? is floating around."
      },
      {
        "jp_string": "？？？は　水の流れにさらわれた！",
        "en_string": "??? was taken by a current!"
      },
      {
        "jp_string": "さかなの行動時 時々 くいつき度が減らない",
        "en_string": "When fish act, sometimes won't decrease the bite chance."
      },
      {
        "jp_string": "くいつき度がなくなった時 一度だけ復活",
        "en_string": "Revive one time when biting chance reaches 0."
      },
      {
        "jp_string": "魚行動で くいつき度が減った時 引き寄せる",
        "en_string": "When fish act, attract when the bite chance goes down."
      }
    ]
  }
]