[
  {
    "hex_start": "CD AB 00 00 00 00 00 00 00 00 00 00 00 00 46 4F 4F 54 10 00 00 00 00 00 00 00 00 00 00 00 54 45 58 54 10 00 00 00 60 04 00 00 00 00 00 00",
    "strings": [
      {
        "jp_string": "ここまでのおこないを 冒険の書に　記録しますか？ <yesno><break>",
        "en_string": ""
      },
      {
        "jp_string": "記録しました！",
        "en_string": ""
      },
      {
        "jp_string": "冒険の書に　記録しています……。 電源ボタンや　リセットボタンに さわらないでください。 <break>",
        "en_string": ""
      },
      {
        "jp_string": "ドラゴンクエストⅩ　オンライン",
        "en_string": ""
      },
      {
        "jp_string": "ドラゴンクエストⅩ オンラインのセーブデータ",
        "en_string": ""
      },
      {
        "jp_string": "皆をつないで 世界がつながる",
        "en_string": ""
      },
      {
        "jp_string": "ドラゴンクエストⅩ オンライン",
        "en_string": ""
      }
    ]
  }
]